Metadata-Version: 2.1
Name: odoo9-addon-account-mass-reconcile-ref-deep-search
Version: 9.0.1.0.0.99.dev80
Summary: Mass Reconcile Ref Deep Search
Home-page: http://www.camptocamp.com
Author: Camptocamp,Odoo Community Association (OCA)
Author-email: support@odoo-community.org
License: UNKNOWN
Platform: UNKNOWN
Classifier: Programming Language :: Python
Classifier: Framework :: Odoo
Requires-Python: ~=2.7
Requires-Dist: odoo9-addon-account-mass-reconcile
Requires-Dist: odoo (<9.1a,>=9.0a)
